{
	"note": [
	"1. Student must take and pass a pretest.",
	"2. We offer 4 two-week Units, students must enroll by Unit."
	],
	"notAvailable": "Sorry, afternoon advanced writing boot camp are only available for those whose incoming grade is G3 or higher.",
	"class_size": "4-8 students",
	"price_per_class": 20,
	"grades": ["G3", "G4", "G5", "G6", "G7", "G8", "G9", "G10", "G11", "G12"],
	"G3": [{
		"display_name": "Advanced Writing G3",
		"database_name": "Advanced_Writing_G3",
		"conflict_test": [
	        { "name": "advanced writing boot camp", "weekday": "Mon", "time": [115.30, 116.30] },
	        { "name": "advanced writing boot camp", "weekday": "Wed", "time": [315.30, 316.30] }
	        ],
		"weekday": ["Mon", "Wed"],
		"display_time": "3:30 PM-4:30 PM",
		"database_time": [15.30, 16.30],
		"class_size": [4, 8],
		"price_per_class": 20
		}],
		"G4": [{
			"display_name": "Advanced Writing G4",
			"database_name": "Advanced_Writing_G4",
			"conflict_test": [
	        { "name": "advanced writing boot camp", "weekday": "Mon", "time": [113.30, 114.30] },
	        { "name": "advanced writing boot camp", "weekday": "Wed", "time": [313.30, 314.30] }
	        ],
			"weekday": ["Mon", "Wed"],
			"display_time": "1:30 PM-2:30 PM",
			"database_time": [13.30, 14.30],
			"class_size": [4, 8],
			"price_per_class": 20
			}],
			"G5": [{
				"display_name": "Advanced Writing G5",
				"database_name": "Advanced_Writing_G5",
				"conflict_test": [
	        { "name": "advanced writing boot camp", "weekday": "Mon", "time": [114.30, 115.30] },
	        { "name": "advanced writing boot camp", "weekday": "Wed", "time": [314.30, 315.30] }
	        ],
				"weekday": ["Mon", "Wed"],
				"display_time": "2:30 PM-3:30 PM",
				"database_time": [14.30, 15.30],
				"class_size": [4, 8],
				"price_per_class": 20
				}],
				"G6": [{
					"display_name": "Advanced Writing Middle School",
					"database_name": "Advanced_Writing_MiddleSchool",
					"conflict_test": [
	        { "name": "advanced writing boot camp", "weekday": "Mon", "time": [116.30, 117.30] },
	        { "name": "advanced writing boot camp", "weekday": "Wed", "time": [316.30, 317.30] }
	        ],
					"weekday": ["Mon", "Wed"],
					"display_time": "4:30 PM-5:30 PM",
					"database_time": [16.30, 17.30],
					"class_size": [4, 8],
					"price_per_class": 20
					}],
					"G7": [{
						"display_name": "Advanced Writing Middle School",
						"database_name": "Advanced_Writing_MiddleSchool",
						"conflict_test": [
	        { "name": "advanced writing boot camp", "weekday": "Mon", "time": [116.30, 117.30] },
	        { "name": "advanced writing boot camp", "weekday": "Wed", "time": [316.30, 317.30] }
	        ],
						"weekday": ["Mon", "Wed"],
						"display_time": "4:30 PM-5:30 PM",
						"database_time": [16.30, 17.30],
						"class_size": [4, 8],
						"price_per_class": 20
						}],
						"G8": [{
							"display_name": "Advanced Writing Middle School",
							"database_name": "Advanced_Writing_MiddleSchool",
							"conflict_test": [
	        { "name": "advanced writing boot camp", "weekday": "Mon", "time": [116.30, 117.30] },
	        { "name": "advanced writing boot camp", "weekday": "Wed", "time": [316.30, 317.30] }
	        ],
							"weekday": ["Mon", "Wed"],
							"display_time": "4:30 PM-5:30 PM",
							"database_time": [16.30, 17.30],
							"class_size": [4, 8],
							"price_per_class": 20
							}],
							"G9": [{
								"display_name": "Advanced Writing Middle School",
								"database_name": "Advanced_Writing_MiddleSchool",
								"conflict_test": [
	        { "name": "advanced writing boot camp", "weekday": "Mon", "time": [116.30, 117.30] },
	        { "name": "advanced writing boot camp", "weekday": "Wed", "time": [316.30, 317.30] }
	        ],
								"weekday": ["Mon", "Wed"],
								"display_time": "4:30 PM-5:30 PM",
								"database_time": [16.30, 17.30],
								"class_size": [4, 8],
								"price_per_class": 20
								}],
								"G10": [{
									"display_name": "Advanced Writing Middle School",
									"database_name": "Advanced_Writing_MiddleSchool",
									"conflict_test": [
	        { "name": "advanced writing boot camp", "weekday": "Mon", "time": [116.30, 117.30] },
	        { "name": "advanced writing boot camp", "weekday": "Wed", "time": [316.30, 317.30] }
	        ],
									"weekday": ["Mon", "Wed"],
									"display_time": "4:30 PM-5:30 PM",
									"database_time": [16.30, 17.30],
									"class_size": [4, 8],
									"price_per_class": 20
									}],
									"G11": [{
										"display_name": "Advanced Writing Middle School",
										"database_name": "Advanced_Writing_MiddleSchool",
										"conflict_test": [
	        { "name": "advanced writing boot camp", "weekday": "Mon", "time": [116.30, 117.30] },
	        { "name": "advanced writing boot camp", "weekday": "Wed", "time": [316.30, 317.30] }
	        ],
										"weekday": ["Mon", "Wed"],
										"display_time": "4:30 PM-5:30 PM",
										"database_time": [16.30, 17.30],
										"class_size": [4, 8],
										"price_per_class": 20
										}],
										"G12": [{
											"display_name": "Advanced Writing Middle School",
											"database_name": "Advanced_Writing_MiddleSchool",
											"conflict_test": [
	        { "name": "advanced writing boot camp", "weekday": "Mon", "time": [116.30, 117.30] },
	        { "name": "advanced writing boot camp", "weekday": "Wed", "time": [316.30, 317.30] }
	        ],
											"weekday": ["Mon", "Wed"],
											"display_time": "4:30 PM-5:30 PM",
											"database_time": [16.30, 17.30],
											"class_size": [4, 8],
											"price_per_class": 20		
											}]
										}